{"trial_id": "0712", "hyperparameters": {"space": [{"class_name": "Int", "config": {"name": "layer1", "default": null, "conditions": [], "min_value": 15, "max_value": 21, "step": 1, "sampling": "linear"}}, {"class_name": "Choice", "config": {"name": "activation", "default": "relu", "conditions": [], "values": ["relu", "tanh"], "ordered": false}}, {"class_name": "Int", "config": {"name": "layer2", "default": null, "conditions": [], "min_value": 10, "max_value": 15, "step": 1, "sampling": "linear"}}, {"class_name": "Int", "config": {"name": "layer3", "default": null, "conditions": [], "min_value": 5, "max_value": 10, "step": 1, "sampling": "linear"}}, {"class_name": "Int", "config": {"name": "layer4", "default": null, "conditions": [], "min_value": 2, "max_value": 5, "step": 1, "sampling": "linear"}}, {"class_name": "Choice", "config": {"name": "learning_rate", "default": 0.01, "conditions": [], "values": [0.01, 0.001, 0.0001], "ordered": true}}], "values": {"layer1": 18, "activation": "relu", "layer2": 14, "layer3": 8, "layer4": 5, "learning_rate": 0.001, "tuner/epochs": 84, "tuner/initial_epoch": 0, "tuner/bracket": 1, "tuner/round": 0}}, "metrics": {"metrics": {"loss": {"direction": "min", "observations": [{"value": [0.3328942358493805], "step": 56}]}, "accuracy": {"direction": "max", "observations": [{"value": [0.8422729969024658], "step": 56}]}, "val_loss": {"direction": "min", "observations": [{"value": [0.3330249786376953], "step": 56}]}, "val_accuracy": {"direction": "max", "observations": [{"value": [0.8478873372077942], "step": 56}]}}}, "score": 0.8478873372077942, "best_step": 56, "status": "COMPLETED", "message": null}